[
  {
    "sprintId": "54825baf-114e-46d3-8ffc-9b8d13986a68",
    "title": "Sprint 3 Retrospective",
    "template": "start_stop_continue",
    "phase": "action_items",
    "isAnonymous": false,
    "createdAt": "2026-03-20T19:40:10.645Z",
    "updatedAt": "2026-03-20T19:40:10.645Z",
    "id": "2dbed858-1943-4ccc-8073-331252ba4cf7"
  },
  {
    "sprintId": "3b991b3c-be7a-4977-a395-096ba6c33c04",
    "title": "Sprint 4 Retrospective",
    "template": "mad_sad_glad",
    "phase": "reflect",
    "isAnonymous": false,
    "createdAt": "2026-03-20T19:40:10.645Z",
    "updatedAt": "2026-03-20T19:40:10.645Z",
    "id": "9c63dd53-8ee3-406a-8233-48035cc7e1a1"
  }
]