[
  {
    "name": "Engineering",
    "description": "Top-level engineering function",
    "parentTeamId": null,
    "color": "var(--color-team-1)",
    "createdAt": "2026-03-20T19:40:10.638Z",
    "updatedAt": "2026-03-20T19:40:10.639Z",
    "id": "e03b365f-cad3-4e15-9764-bca6bb036463"
  },
  {
    "name": "Platform",
    "description": "Shared services and foundations",
    "parentTeamId": "e03b365f-cad3-4e15-9764-bca6bb036463",
    "color": "var(--color-team-2)",
    "createdAt": "2026-03-20T19:40:10.640Z",
    "updatedAt": "2026-03-20T19:40:10.640Z",
    "id": "c6c8ee05-a7b7-4c10-8625-16bf16823fbb"
  },
  {
    "name": "Product",
    "description": "Feature delivery teams",
    "parentTeamId": "e03b365f-cad3-4e15-9764-bca6bb036463",
    "color": "var(--color-team-3)",
    "createdAt": "2026-03-20T19:40:10.640Z",
    "updatedAt": "2026-03-20T19:40:10.640Z",
    "id": "3e2f1320-ecf1-40a9-9123-71d96868bed1"
  },
  {
    "name": "Infrastructure",
    "description": "Cloud and reliability",
    "parentTeamId": "c6c8ee05-a7b7-4c10-8625-16bf16823fbb",
    "color": "var(--color-team-4)",
    "createdAt": "2026-03-20T19:40:10.641Z",
    "updatedAt": "2026-03-20T19:40:10.641Z",
    "id": "c73a05d2-4fbe-4992-b5cd-22a3b3ccf7d3"
  },
  {
    "name": "Mobile",
    "description": "iOS and Android experience",
    "parentTeamId": "3e2f1320-ecf1-40a9-9123-71d96868bed1",
    "color": "var(--color-team-5)",
    "createdAt": "2026-03-20T19:40:10.641Z",
    "updatedAt": "2026-03-20T19:40:10.641Z",
    "id": "4f51b328-aba9-4e1c-a5cd-a80b5dda794a"
  },
  {
    "name": "Cloud Ops",
    "description": "Runtime operations and cloud governance",
    "parentTeamId": "c73a05d2-4fbe-4992-b5cd-22a3b3ccf7d3",
    "color": "var(--color-team-6)",
    "createdAt": "2026-03-20T19:40:10.641Z",
    "updatedAt": "2026-03-20T19:40:10.641Z",
    "id": "e16e9398-99ef-4dd9-93c7-e54b253c1d0c"
  }
]